pyside_socket_async/__init__.py
pyside_socket_async/cache/__init__.py
pyside_socket_async/config/__init__.py
pyside_socket_async/config/scoket_config.py
pyside_socket_async/constants/__init__.py
pyside_socket_async/constants/task_status.py
pyside_socket_async/model/__init__.py
pyside_socket_async/model/http_response.py
pyside_socket_async/model/request.py
pyside_socket_async/model/response_error.py
pyside_socket_async/model/result.py
pyside_socket_async/socket_thread/__init__.py
pyside_socket_async/socket_thread/socket_thread.py
pyside_socket_async/socket_thread/task.py
pyside_socket_async/tasks_service/__init__.py
pyside_socket_async/tasks_service/serice_base.py
pyside_socket_async/tasks_service/service_base.py
pyside_socket_async/tasks_service/task_base.py
pyside_socket_async/tasks_service/tasks.py
pyside_socket_async/tasks_service/ts.py
pyside_socket_async/utils/__init__.py
pyside_socket_async/utils/b64.py
pyside_socket_async/utils/http_client.py
pyside_socket_async/utils/parallel_tasks.py
pyside_socket_async/utils/socket_client.py
pyside_socket_async-0.2.2.dist-info/LICENSE
pyside_socket_async-0.2.2.dist-info/METADATA
pyside_socket_async-0.2.2.dist-info/WHEEL
pyside_socket_async-0.2.2.dist-info/top_level.txt
pyside_socket_async-0.2.2.dist-info/RECORD
