Metadata-Version: 2.1
Name: pyside_socket_async
Version: 0.2.2
Summary: 本框架旨在将运行时间较长的方法在一个线程中执行，最后通过插槽将结果返回给界面，其中涉及 socket 的通信，Qt多线程，Qt插槽，以及任务注册的概念。
Home-page: https://gitee.com/cai-xinpenge/pyside_socket_async
Author: chakcy
Author-email: 947105045@qq.com
Classifier: Programming Language :: Python :: 3
Classifier: License :: OSI Approved :: MIT License
Classifier: Operating System :: OS Independent
Requires-Python: >=3.9
License-File: LICENSE
Requires-Dist: pydantic>=2.9.1
Requires-Dist: PySide6>=6.7.2
Requires-Dist: requests>=2.32.3
